expan/__init__.py
expan/core/__init__.py
expan/core/binning.py
expan/core/debugging.py
expan/core/experiment.py
expan/core/experimentdata.py
expan/core/results.py
expan/core/statistics.py
expan/core/util.py
expan/core/version.py
expan/data/__init__.py
expan/data/csv_fetcher.py
tests/__init__.py
tests/tests_core/__init__.py
tests/tests_core/test_binning.py
tests/tests_core/test_data.py
tests/tests_core/test_debugging.py
tests/tests_core/test_experiment.py
tests/tests_core/test_results.py
tests/tests_core/test_statistics.py
tests/tests_core/test_util.py
tests/tests_core/framingham_data.csv
tests/tests_core/framingham_heart_study_exam7.csv
tests/tests_core/framingham_statistics.csv
tests/tests_core/normtemp.dat.txt.gz
tests/tests_core/test-logging.conf
tests/tests_data/__init__.py
tests/tests_data/test_csv_fetcher.py
expan-0.2.4.dist-info/top_level.txt
expan-0.2.4.dist-info/METADATA
expan-0.2.4.dist-info/DESCRIPTION.rst
expan-0.2.4.dist-info/metadata.json
expan-0.2.4.dist-info/WHEEL
expan-0.2.4.dist-info/RECORD
