Metadata-Version: 2.0
Name: expan
Version: 0.2.4
Summary: Experiment Analysis Library
Home-page: https://github.com/zalando/expan
Author: Zalando SE
Author-email: octopus@zalando.de
License: MIT
Keywords: expan
Platform: UNKNOWN
Classifier: Development Status :: 2 - Pre-Alpha
Classifier: Intended Audience :: Developers
Classifier: Intended Audience :: Science/Research
Classifier: License :: OSI Approved :: MIT License
Classifier: Natural Language :: English
Classifier: Programming Language :: Python :: 2.7
Requires-Dist: pandas (>=0.17.1)
Requires-Dist: scipy (>=0.17.0)
Requires-Dist: numpy (>=1.10.4)
Requires-Dist: simplejson (>=3.8.2)
